[
  {
    "id": "default",
    "name": "Evento Público (Base)",
    "event_type": "public",
    "event_date": null,
    "photos_to_take": 4,
    "countdown_seconds": 5,
    "auto_reset_seconds": 30,
    "audio_enabled": true,
    "voice_rate": 1.0,
    "voice_pitch": 1.0,
    "voice_volume": 1.0,
    "design_id": null,
    "design_name": null,
    "design_path": null,
    "design_preview_url": null,
    "is_active": true,
    "is_default": true,
    "created_at": "2025-11-09T11:48:34.087554",
    "updated_at": "2025-11-09T11:49:23.633857",
    "notes": "Configuración base para eventos públicos",
    "client_name": null,
    "client_contact": null
  }
]